{
    "defaultSeverity": "error",
    "extends": [],
    "jsRules": {},
    "rules": {
        // https://palantir.github.io/tslint/rules/adjacent-overload-signatures/
        "adjacent-overload-signatures": true,
        // https://palantir.github.io/tslint/rules/ban-types/
        "ban-types": false,
        // https://palantir.github.io/tslint/rules/member-access/
        "member-access": [
            true,
            "no-public",
            "check-accessor",
            "check-constructor"
        ],
        // https://palantir.github.io/tslint/rules/member-ordering/
        "member-ordering": [
            true,
            {
                "order": [
                    "public-static-field",
                    "protected-static-field",
                    "private-static-field",
                    "public-instance-field",
                    "protected-instance-field",
                    "private-instance-field",
                    "constructor",
                    "public-static-method",
                    "protected-static-method",
                    "private-static-method",
                    "public-instance-method",
                    "protected-instance-method",
                    "private-instance-method"
                ]
            }
        ],
        // https://palantir.github.io/tslint/rules/no-any/
        "no-any": true,
        // https://palantir.github.io/tslint/rules/no-empty-interface/
        "no-empty-interface": true,
        // https://palantir.github.io/tslint/rules/no-import-side-effect/
        "no-import-side-effect": [true, {"ignore-module": "(\\.html|\\.pug|\\.jade|\\.ejs|\\.hbs|\\.css|\\.less|\\.sass|\\.scss|\\.stylus|\\.styl)$"}],
        "no-inferrable-types": false,
        "no-internal-module": true,
        "no-namespace": [true, "allow-declarations"],
        "no-non-null-assertion": true,
        "no-reference": true,
        "no-unnecessary-type-assertion": true,
        "no-var-requires": true,
        "only-arrow-functions": [true, "allow-declarations", "allow-named-functions"],
        "typedef": [true, "call-signature", "parameter", "member-variable-declaration"],
        "typedef-whitespace": [
            true,
            {
                "call-signature": "nospace",
                "index-signature": "nospace",
                "parameter": "nospace",
                "property-declaration": "nospace",
                "variable-declaration": "nospace"
            }
        ],
        "unified-signatures": true,
        "await-promise": false,
        "ban": false,
        "curly": [true, "ignore-same-line"],
        "forin": false,
        "import-blacklist": false,
        "label-position": true,
        "no-arg": true,
        "no-bitwise": false,
        "no-conditional-assignment": true,
        "no-console": false,
        "no-construct": true,
        "no-debugger": false,
        "no-duplicate-super": true
    },
    "rulesDirectory": []
}
